{"id": "21432673-d635-4a94-9473-686e92805330", "code": "# EVOLVE-BLOCK-START\n\"\"\"Function minimization example for OpenEvolve\"\"\"\nimport numpy as np\n\ndef search_algorithm(iterations=1000, bounds=(-5, 5)):\n    \"\"\"\n    A search algorithm that balances exploration and exploitation to find function minima.\n\n    Args:\n        iterations: Number of iterations to run\n        bounds: Bounds for the search space (min, max)\n\n    Returns:\n        Tuple of (best_x, best_y, best_value)\n    \"\"\"\n    # Cache bounds for readability and performance\n    lower, upper = bounds\n    range_size = upper - lower\n    \n    # Initialize with random point (simplified)\n    best_x, best_y = np.random.uniform(lower, upper, 2)\n    best_value = evaluate_function(best_x, best_y)\n\n    for iteration in range(iterations):\n        # Balance exploration (global search) and exploitation (local refinement)\n        if np.random.random() < 0.7:  # 70% local exploitation\n            # Adaptive step size that decreases over time\n            step = 0.1 * (1 - iteration/iterations) * range_size\n            x, y = np.clip([best_x, best_y] + np.random.normal(0, step, 2), lower, upper)\n        else:  # 30% global exploration\n            x, y = np.random.uniform(lower, upper, 2)\n            \n        value = evaluate_function(x, y)\n\n        if value < best_value:\n            best_value = value\n            best_x, best_y = x, y\n\n    return best_x, best_y, best_value\n\n\n# EVOLVE-BLOCK-END\n\n\n# This part remains fixed (not evolved)\ndef evaluate_function(x, y):\n    \"\"\"The complex function we're trying to minimize\"\"\"\n    return np.sin(x) * np.cos(y) + np.sin(x * y) + (x**2 + y**2) / 20\n\n\ndef run_search():\n    x, y, value = search_algorithm()\n    return x, y, value\n\n\nif __name__ == \"__main__\":\n    x, y, value = run_search()\n    print(f\"Found minimum at ({x}, {y}) with value {value}\")\n", "language": "python", "parent_id": "ad672793-7945-446d-b00e-f5978fb9a399", "generation": 4, "timestamp": 1755446669.3550963, "iteration_found": 72, "metrics": {"runs_successfully": 1.0, "value_score": 0.9899554000759104, "distance_score": 0.7132611451902185, "overall_score": 0.24121837845533667, "standard_deviation_score": 0.5498305071676899, "speed_score": 1.0, "reliability_score": 1.0, "combined_score": 0.8060918922766832, "success_rate": 1.0}, "complexity": 0.0, "diversity": 0.0, "metadata": {"changes": "Change 1: Replace 4 lines with 3 lines\nChange 2: Replace 3 lines with 7 lines\nChange 3: Replace 8 lines with 8 lines", "parent_metrics": {"runs_successfully": 1.0, "value_score": 0.9996774362130691, "distance_score": 0.9977952536293356, "overall_score": 0.9997554178460961, "standard_deviation_score": 0.9983082389281939, "speed_score": 1.0, "reliability_score": 1.0, "combined_score": 0.9987770892304805, "success_rate": 1.0}, "island": 0}, "artifacts_json": null, "artifact_dir": null, "prompts": {"diff_user": {"system": "You are an expert coder helping to improve programs through evolution.", "user": "# Current Program Information\n- Current performance metrics: - runs_successfully: 1.0000\n- value_score: 0.9997\n- distance_score: 0.9978\n- overall_score: 0.9998\n- standard_deviation_score: 0.9983\n- speed_score: 1.0000\n- reliability_score: 1.0000\n- combined_score: 0.9988\n- success_rate: 1.0000\n- Areas identified for improvement: - Consider simplifying the code to improve readability and maintainability\n- Metrics showing improvement: value_score, distance_score, overall_score, standard_deviation_score, combined_score. Consider continuing with similar changes.\n\n\n\n# Program Evolution History\n## Previous Attempts\n\n### Attempt 3\n- Changes: Unknown changes\n- Performance: runs_successfully: 1.0000, value_score: 0.9996, distance_score: 0.9944, overall_score: 0.9994, standard_deviation_score: 0.9956, speed_score: 1.0000, reliability_score: 1.0000, combined_score: 0.9970, success_rate: 1.0000\n- Outcome: Improvement in all metrics\n\n\n### Attempt 2\n- Changes: Unknown changes\n- Performance: runs_successfully: 1.0000, value_score: 0.9997, distance_score: 0.9959, overall_score: 0.9995, standard_deviation_score: 0.9964, speed_score: 1.0000, reliability_score: 1.0000, combined_score: 0.9977, success_rate: 1.0000\n- Outcome: Improvement in all metrics\n\n\n### Attempt 1\n- Changes: Unknown changes\n- Performance: runs_successfully: 1.0000, value_score: 0.9997, distance_score: 0.9978, overall_score: 0.9998, standard_deviation_score: 0.9983, speed_score: 1.0000, reliability_score: 1.0000, combined_score: 0.9988, success_rate: 1.0000\n- Outcome: Improvement in all metrics\n\n## Top Performing Programs\n\n### Program 1 (Score: 0.9994)\n```python\n# EVOLVE-BLOCK-START\n\"\"\"Function minimization example for OpenEvolve\"\"\"\nimport numpy as np\nfrom typing import Tuple\n\ndef search_algorithm(iterations: int = 1000, bounds: Tuple[float, float] = (-5, 5)) -> Tuple[float, float, float]:\n    \"\"\"\n    A search algorithm that balances exploration and exploitation to find function minima.\n\n    Args:\n        iterations: Number of iterations to run\n        bounds: Bounds for the search space (min, max)\n\n    Returns:\n        Tuple of (best_x, best_y, best_value)\n    \"\"\"\n    # Initialize with random point (simplified)\n    best_x, best_y = np.random.uniform(*bounds, 2)\n    best_value = evaluate_function(best_x, best_y)\n\n    for _ in range(iterations):\n        # Balance exploration (global search) and exploitation (local refinement)\n        if np.random.random() < 0.7:  # 70% local exploitation\n            # Adaptive step size that decreases over time\n            step = 0.1 * (1 - _/iterations) * (bounds[1] - bounds[0])\n            x, y = np.clip([best_x, best_y] + np.random.normal(0, step, 2), bounds[0], bounds[1])\n        else:  # 30% global exploration\n            x, y = np.random.uniform(*bounds, 2)\n            \n        value = evaluate_function(x, y)\n\n        if value < best_value:\n            best_value = value\n            best_x, best_y = x, y\n\n    return best_x, best_y, best_value\n\n\n# EVOLVE-BLOCK-END\n\n\n# This part remains fixed (not evolved)\ndef evaluate_function(x, y):\n    \"\"\"The complex function we're trying to minimize\"\"\"\n    return np.sin(x) * np.cos(y) + np.sin(x * y) + (x**2 + y**2) / 20\n\n\ndef run_search():\n    x, y, value = search_algorithm()\n    return x, y, value\n\n\nif __name__ == \"__main__\":\n    x, y, value = run_search()\n    print(f\"Found minimum at ({x}, {y}) with value {value}\")\n\n```\nKey features: Performs well on runs_successfully (1.0000), Performs well on value_score (0.9997), Performs well on distance_score (0.9978), Performs well on overall_score (0.9998), Performs well on standard_deviation_score (0.9983), Performs well on speed_score (1.0000), Performs well on reliability_score (1.0000), Performs well on combined_score (0.9988), Performs well on success_rate (1.0000)\n\n\n### Program 2 (Score: 0.9988)\n```python\n# EVOLVE-BLOCK-START\n\"\"\"Function minimization example for OpenEvolve\"\"\"\nimport numpy as np\n\n\ndef search_algorithm(iterations=1000, bounds=(-5, 5)):\n    \"\"\"\n    A simple random search algorithm that often gets stuck in local minima.\n\n    Args:\n        iterations: Number of iterations to run\n        bounds: Bounds for the search space (min, max)\n\n    Returns:\n        Tuple of (best_x, best_y, best_value)\n    \"\"\"\n    # Initialize with random point (simplified)\n    best_x, best_y = np.random.uniform(bounds[0], bounds[1], 2)\n    best_value = evaluate_function(best_x, best_y)\n\n    for _ in range(iterations):\n        # Hybrid search with local exploration and global search\n        if np.random.random() < 0.7:  # 70% chance for local exploration\n            # Explore around best point with decreasing step size\n            step = 0.1 * (1 - _/iterations) * (bounds[1] - bounds[0])\n            x = np.clip(best_x + np.random.normal(0, step), bounds[0], bounds[1])\n            y = np.clip(best_y + np.random.normal(0, step), bounds[0], bounds[1])\n        else:  # 30% chance for global exploration\n            x, y = np.random.uniform(bounds[0], bounds[1], 2)\n            \n        value = evaluate_function(x, y)\n\n        if value < best_value:\n            best_value = value\n            best_x, best_y = x, y\n\n    return best_x, best_y, best_value\n\n\n# EVOLVE-BLOCK-END\n\n\n# This part remains fixed (not evolved)\ndef evaluate_function(x, y):\n    \"\"\"The complex function we're trying to minimize\"\"\"\n    return np.sin(x) * np.cos(y) + np.sin(x * y) + (x**2 + y**2) / 20\n\n\ndef run_search():\n    x, y, value = search_algorithm()\n    return x, y, value\n\n\nif __name__ == \"__main__\":\n    x, y, value = run_search()\n    print(f\"Found minimum at ({x}, {y}) with value {value}\")\n\n```\nKey features: Performs well on runs_successfully (1.0000), Performs well on value_score (0.9997), Performs well on distance_score (0.9959), Performs well on overall_score (0.9995), Performs well on standard_deviation_score (0.9964), Performs well on speed_score (1.0000), Performs well on reliability_score (1.0000), Performs well on combined_score (0.9977), Performs well on success_rate (1.0000)\n\n\n### Program 3 (Score: 0.9985)\n```python\n# EVOLVE-BLOCK-START\n\"\"\"Function minimization example for OpenEvolve\"\"\"\nimport numpy as np\n\n\ndef search_algorithm(iterations=1000, bounds=(-5, 5)):\n    \"\"\"\n    A simple random search algorithm that often gets stuck in local minima.\n\n    Args:\n        iterations: Number of iterations to run\n        bounds: Bounds for the search space (min, max)\n\n    Returns:\n        Tuple of (best_x, best_y, best_value)\n    \"\"\"\n    # Initialize with random point (simplified)\n    best_x, best_y = np.random.uniform(bounds[0], bounds[1], 2)\n    best_value = evaluate_function(best_x, best_y)\n\n    for _ in range(iterations):\n        # Hybrid search with local exploration and global exploration\n        if np.random.random() < 0.7:  # 70% local exploration around best point\n            # Explore with decreasing step size\n            step = 0.1 * (1 - _/iterations) * (bounds[1] - bounds[0])\n            x = np.clip(best_x + np.random.normal(0, step), bounds[0], bounds[1])\n            y = np.clip(best_y + np.random.normal(0, step), bounds[0], bounds[1])\n        else:  # 30% global exploration\n            x, y = np.random.uniform(bounds[0], bounds[1], 2)\n            \n        value = evaluate_function(x, y)\n\n        if value < best_value:\n            best_value = value\n            best_x, best_y = x, y\n\n    return best_x, best_y, best_value\n\n\n# EVOLVE-BLOCK-END\n\n\n# This part remains fixed (not evolved)\ndef evaluate_function(x, y):\n    \"\"\"The complex function we're trying to minimize\"\"\"\n    return np.sin(x) * np.cos(y) + np.sin(x * y) + (x**2 + y**2) / 20\n\n\ndef run_search():\n    x, y, value = search_algorithm()\n    return x, y, value\n\n\nif __name__ == \"__main__\":\n    x, y, value = run_search()\n    print(f\"Found minimum at ({x}, {y}) with value {value}\")\n\n```\nKey features: Performs well on runs_successfully (1.0000), Performs well on value_score (0.9996), Performs well on distance_score (0.9944), Performs well on overall_score (0.9994), Performs well on standard_deviation_score (0.9956), Performs well on speed_score (1.0000), Performs well on reliability_score (1.0000), Performs well on combined_score (0.9970), Performs well on success_rate (1.0000)\n\n\n\n\n## Diverse Programs\n\n### Program D1 (Score: 0.9970)\n```python\n# EVOLVE-BLOCK-START\n\"\"\"Function minimization example for OpenEvolve\"\"\"\nimport numpy as np\n\n\ndef search_algorithm(iterations=1000, bounds=(-5, 5)):\n    \"\"\"\n    Adaptive search algorithm balancing global exploration and local exploitation.\n\n    Efficiently explores search space by starting with broad exploration and\n    gradually shifting to focused exploitation around promising solutions.\n\n    Args:\n        iterations: Number of iterations to run\n        bounds: Bounds for the search space (min, max)\n\n    Returns:\n        Tuple of (best_x, best_y, best_value) - coordinates and value of minimum found\n    \"\"\"\n    # Initialize with a random point\n    best_x, best_y = np.random.uniform(*bounds, 2)\n    best_value = evaluate_function(best_x, best_y)\n\n    for _ in range(iterations):\n        # Adaptive search strategy: balance exploration vs exploitation\n        # Start with mostly exploration, gradually shift to exploitation\n        exploration_ratio = max(0.3, 1.0 - _/iterations)  # Decreases from 1.0 to 0.3\n        \n        if np.random.random() < exploration_ratio:\n            # Global exploration: search entire bounds\n            x, y = np.random.uniform(*bounds, 2)\n        else:\n            # Local exploitation: refine around best solution with decreasing step size\n            step_size = (bounds[1] - bounds[0]) * (1 - _/iterations)\n            x = best_x + np.random.normal(0, step_size/3)\n            y = best_y + np.random.normal(0, step_size/3)\n            x, y = np.clip([x, y], bounds[0], bounds[1])\n            \n        value = evaluate_function(x, y)\n\n        if value < best_value:\n            best_value = value\n            best_x, best_y = x, y\n\n    return best_x, best_y, best_value\n\n\n# EVOLVE-BLOCK-END\n\n\n# This part remains fixed (not evolved)\ndef evaluate_function(x, y):\n    \"\"\"The complex function we're trying to minimize\"\"\"\n    return np.sin(x) * np.cos(y) + np.sin(x * y) + (x**2 + y**2) / 20\n\n\ndef run_search():\n    x, y, value = search_algorithm()\n    return x, y, value\n\n\nif __name__ == \"__main__\":\n    x, y, value = run_search()\n    print(f\"Found minimum at ({x}, {y}) with value {value}\")\n\n```\nKey features: Alternative approach to runs_successfully, Alternative approach to value_score\n\n\n### Program D2 (Score: 0.9970)\n```python\n# EVOLVE-BLOCK-START\n\"\"\"Function minimization example for OpenEvolve\"\"\"\nimport numpy as np\n\n\ndef search_algorithm(iterations=1000, bounds=(-5, 5)):\n    \"\"\"\n    A simple random search algorithm that often gets stuck in local minima.\n\n    Args:\n        iterations: Number of iterations to run\n        bounds: Bounds for the search space (min, max)\n\n    Returns:\n        Tuple of (best_x, best_y, best_value)\n    \"\"\"\n    # Initialize with random point\n    best_x, best_y = np.random.uniform(*bounds, 2)\n    best_value = evaluate_function(best_x, best_y)\n\n    for _ in range(iterations):\n        # Adaptive search: start with exploration, shift to exploitation\n        exploration_ratio = max(0.3, 1.0 - _/iterations)  # Decreases from 1.0 to 0.3\n        if np.random.random() < exploration_ratio:  # Adaptive exploration ratio\n            x, y = np.random.uniform(*bounds, 2)\n        else:  # 80% chance to exploit by searching near best solution\n            # Use decreasing step size for local search\n            step_size = 0.5 * (1 - _/iterations) * (bounds[1] - bounds[0])\n            x = best_x + np.random.normal(0, step_size)\n            y = best_y + np.random.normal(0, step_size)\n            x, y = np.clip(x, bounds[0], bounds[1]), np.clip(y, bounds[0], bounds[1])\n            \n        value = evaluate_function(x, y)\n\n        if value < best_value:\n            best_value = value\n            best_x, best_y = x, y\n\n    return best_x, best_y, best_value\n\n\n# EVOLVE-BLOCK-END\n\n\n# This part remains fixed (not evolved)\ndef evaluate_function(x, y):\n    \"\"\"The complex function we're trying to minimize\"\"\"\n    return np.sin(x) * np.cos(y) + np.sin(x * y) + (x**2 + y**2) / 20\n\n\ndef run_search():\n    x, y, value = search_algorithm()\n    return x, y, value\n\n\nif __name__ == \"__main__\":\n    x, y, value = run_search()\n    print(f\"Found minimum at ({x}, {y}) with value {value}\")\n\n```\nKey features: Alternative approach to runs_successfully, Alternative approach to value_score\n\n## Inspiration Programs\n\nThese programs represent diverse approaches and creative solutions that may inspire new ideas:\n\n### Inspiration 1 (Score: 0.9859, Type: High-Performer)\n```python\n# EVOLVE-BLOCK-START\n\"\"\"Function minimization example for OpenEvolve\"\"\"\nimport numpy as np\n\n\ndef search_algorithm(iterations=1000, bounds=(-5, 5)):\n    \"\"\"\n    Random search algorithm with adaptive exploration.\n\n    Balances local exploration and global search to find better minima.\n\n    Args:\n        iterations: Number of iterations to run\n        bounds: Bounds for the search space (min, max)\n\n    Returns:\n        Tuple of (best_x, best_y, best_value)\n    \"\"\"\n    # Initialize with a random point\n    best_x, best_y = np.random.uniform(bounds[0], bounds[1], size=2)\n    best_value = evaluate_function(best_x, best_y)\n\n    for _ in range(iterations):\n        # Generate candidate point\n        # Adaptive search: balance local exploration and global search\n        if np.random.random() < 0.2:  # 20% global exploration\n            x, y = np.random.uniform(bounds[0], bounds[1], size=2)\n        else:  # 80% local refinement around best found solution\n            search_range = (bounds[1] - bounds[0]) * 0.1\n            x = np.clip(best_x + np.random.normal(0, search_range), bounds[0], bounds[1])\n            y = np.clip(best_y + np.random.normal(0, search_range), bounds[0], bounds[1])\n        value = evaluate_function(x, y)\n\n        if value < best_value:\n            best_value = value\n            best_x, best_y = x, y\n\n    return best_x, best_y, best_value\n\n\n# EVOLVE-BLOCK-END\n\n\n# This part remains fixed (not evolved)\ndef evaluate_function(x, y):\n    \"\"\"The complex function we're trying to minimize\"\"\"\n    return np.sin(x) * np.cos(y) + np.sin(x * y) + (x**2 + y**2) / 20\n\n\ndef run_search():\n    x, y, value = search_algorithm()\n    return x, y, value\n\n\nif __name__ == \"__main__\":\n    x, y, value = run_search()\n    print(f\"Found minimum at ({x}, {y}) with value {value}\")\n\n```\nUnique approach: Excellent runs_successfully (1.000), Excellent value_score (0.997), Excellent distance_score (0.949)\n\n\n### Inspiration 2 (Score: 0.8911, Type: High-Performer)\n```python\n# EVOLVE-BLOCK-START\n\"\"\"Function minimization example for OpenEvolve\"\"\"\nimport numpy as np\n\n\ndef search_algorithm(iterations=1000, bounds=(-5, 5)):\n    \"\"\"\n    A search algorithm balancing exploration and exploitation for function minimization.\n\n    Args:\n        iterations: Number of iterations to run\n        bounds: Bounds for the search space (min, max)\n\n    Returns:\n        Tuple of (best_x, best_y, best_value)\n    \"\"\"\n    # Cache bounds for readability and performance\n    lower, upper = bounds\n    range_size = upper - lower\n    \n    # Initialize with a random point\n    best_x, best_y = np.random.uniform(lower, upper, size=2)\n    best_value = evaluate_function(best_x, best_y)\n\n    for _ in range(iterations):\n        # Balance exploration (global search) and exploitation (local refinement)\n        if np.random.random() < 0.7:  # 70% local exploitation\n            # Adaptive step size that decreases over time\n            step = 0.1 * (1 - _/iterations) * range_size\n            x = np.clip(best_x + np.random.normal(0, step), lower, upper)\n            y = np.clip(best_y + np.random.normal(0, step), lower, upper)\n        else:  # 30% global exploration\n            x, y = np.random.uniform(lower, upper, size=2)\n            \n        value = evaluate_function(x, y)\n\n        if value < best_value:\n            best_value = value\n            best_x, best_y = x, y\n\n    return best_x, best_y, best_value\n\n\n# EVOLVE-BLOCK-END\n\n\n# This part remains fixed (not evolved)\ndef evaluate_function(x, y):\n    \"\"\"The complex function we're trying to minimize\"\"\"\n    return np.sin(x) * np.cos(y) + np.sin(x * y) + (x**2 + y**2) / 20\n\n\ndef run_search():\n    x, y, value = search_algorithm()\n    return x, y, value\n\n\nif __name__ == \"__main__\":\n    x, y, value = run_search()\n    print(f\"Found minimum at ({x}, {y}) with value {value}\")\n\n```\nUnique approach: Modification: Change 1: Replace 13 lines with 17 lines\nChange 2: Replace 5 lines with 5 lines, Excellent runs_successfully (1.000), Excellent value_score (0.990)\n\n\n### Inspiration 3 (Score: 0.8182, Type: High-Performer)\n```python\n# EVOLVE-BLOCK-START\n\"\"\"Function minimization example for OpenEvolve\"\"\"\nimport numpy as np\n\n\ndef search_algorithm(iterations=1000, bounds=(-5, 5)):\n    \"\"\"\n    A simple random search algorithm for function minimization.\n\n    Args:\n        iterations: Number of iterations to run\n        bounds: Bounds for the search space (min, max)\n\n    Returns:\n        Tuple of (best_x, best_y, best_value)\n    \"\"\"\n    # Initialize with random point using vectorized operation\n    best_x, best_y = np.random.uniform(bounds[0], bounds[1], size=2)\n    best_value = evaluate_function(best_x, best_y)\n\n    # Cache bounds values for performance\n    lower_bound, upper_bound = bounds\n    \n    for _ in range(iterations):\n        # Adaptive search strategy: balance exploration and exploitation\n        if np.random.random() < 0.3:  # 30% chance for random exploration\n            x, y = np.random.uniform(lower_bound, upper_bound, size=2)\n        else:  # 70% chance for local refinement around best solution\n            # Narrow search around best solution with adaptive radius\n            radius = (upper_bound - lower_bound) * (1 - _/iterations) * 0.1\n            x = np.clip(best_x + np.random.normal(0, radius), lower_bound, upper_bound)\n            y = np.clip(best_y + np.random.normal(0, radius), lower_bound, upper_bound)\n            \n        value = evaluate_function(x, y)\n\n        if value < best_value:\n            best_value = value\n            best_x, best_y = x, y\n\n    return best_x, best_y, best_value\n\n\n# EVOLVE-BLOCK-END\n\n\n# This part remains fixed (not evolved)\ndef evaluate_function(x, y):\n    \"\"\"The complex function we're trying to minimize\"\"\"\n    return np.sin(x) * np.cos(y) + np.sin(x * y) + (x**2 + y**2) / 20\n\n\ndef run_search():\n    x, y, value = search_algorithm()\n    return x, y, value\n\n\nif __name__ == \"__main__\":\n    x, y, value = run_search()\n    print(f\"Found minimum at ({x}, {y}) with value {value}\")\n\n```\nUnique approach: Modification: Change 1: Replace 8 lines with 18 lines, Excellent runs_successfully (1.000), Excellent value_score (0.962)\n\n\n### Inspiration 4 (Score: 0.9587, Type: High-Performer)\n```python\n# EVOLVE-BLOCK-START\n\"\"\"Function minimization example for OpenEvolve\"\"\"\nimport numpy as np\n\n\ndef search_algorithm(iterations=1000, bounds=(-5, 5)):\n    \"\"\"\n    A simple random search algorithm for function minimization.\n\n    Args:\n        iterations: Number of iterations to run\n        bounds: Bounds for the search space (min, max)\n\n    Returns:\n        Tuple of (best_x, best_y, best_value)\n    \"\"\"\n    # Initialize with random point\n    best_coords = np.random.uniform(bounds[0], bounds[1], size=2)\n    best_x, best_y = best_coords\n    best_value = evaluate_function(best_x, best_y)\n\n    for _ in range(iterations):\n        # Generate candidate solution\n        coords = np.random.uniform(bounds[0], bounds[1], size=2)\n        x, y = coords\n        current_value = evaluate_function(x, y)\n\n        if current_value < best_value:\n            best_value = current_value\n            best_coords = coords\n            best_x, best_y = x, y\n\n    return best_x, best_y, best_value\n\n\n# EVOLVE-BLOCK-END\n\n\n# This part remains fixed (not evolved)\ndef evaluate_function(x, y):\n    \"\"\"The complex function we're trying to minimize\"\"\"\n    return np.sin(x) * np.cos(y) + np.sin(x * y) + (x**2 + y**2) / 20\n\n\ndef run_search():\n    x, y, value = search_algorithm()\n    return x, y, value\n\n\nif __name__ == \"__main__\":\n    x, y, value = run_search()\n    print(f\"Found minimum at ({x}, {y}) with value {value}\")\n\n```\nUnique approach: Modification: Change 1: Replace 12 lines with 15 lines\nChange 2: Replace 3 lines with 11 lines, Excellent runs_successfully (1.000), Excellent value_score (0.963)\n\n\n### Inspiration 5 (Score: 0.9988, Type: High-Performer)\n```python\n# EVOLVE-BLOCK-START\n\"\"\"Function minimization example for OpenEvolve\"\"\"\nimport numpy as np\n\n\ndef search_algorithm(iterations=1000, bounds=(-5, 5)):\n    \"\"\"\n    A simple random search algorithm that often gets stuck in local minima.\n\n    Args:\n        iterations: Number of iterations to run\n        bounds: Bounds for the search space (min, max)\n\n    Returns:\n        Tuple of (best_x, best_y, best_value)\n    \"\"\"\n    # Initialize with random point (simplified)\n    best_x, best_y = np.random.uniform(bounds[0], bounds[1], 2)\n    best_value = evaluate_function(best_x, best_y)\n\n    for _ in range(iterations):\n        # Hybrid search with local exploration and global search\n        if np.random.random() < 0.7:  # 70% chance for local exploration\n            # Explore around best point with decreasing step size\n            step = 0.1 * (1 - _/iterations) * (bounds[1] - bounds[0])\n            x = np.clip(best_x + np.random.normal(0, step), bounds[0], bounds[1])\n            y = np.clip(best_y + np.random.normal(0, step), bounds[0], bounds[1])\n        else:  # 30% chance for global exploration\n            x, y = np.random.uniform(bounds[0], bounds[1], 2)\n            \n        value = evaluate_function(x, y)\n\n        if value < best_value:\n            best_value = value\n            best_x, best_y = x, y\n\n    return best_x, best_y, best_value\n\n\n# EVOLVE-BLOCK-END\n\n\n# This part remains fixed (not evolved)\ndef evaluate_function(x, y):\n    \"\"\"The complex function we're trying to minimize\"\"\"\n    return np.sin(x) * np.cos(y) + np.sin(x * y) + (x**2 + y**2) / 20\n\n\ndef run_search():\n    x, y, value = search_algorithm()\n    return x, y, value\n\n\nif __name__ == \"__main__\":\n    x, y, value = run_search()\n    print(f\"Found minimum at ({x}, {y}) with value {value}\")\n\n```\nUnique approach: Modification: Change 1: Replace 8 lines with 15 lines, Excellent runs_successfully (1.000), Excellent value_score (1.000)\n\n\n\n# Current Program\n```python\n# EVOLVE-BLOCK-START\n\"\"\"Function minimization example for OpenEvolve\"\"\"\nimport numpy as np\nfrom typing import Tuple\n\ndef search_algorithm(iterations: int = 1000, bounds: Tuple[float, float] = (-5, 5)) -> Tuple[float, float, float]:\n    \"\"\"\n    A search algorithm that balances exploration and exploitation to find function minima.\n\n    Args:\n        iterations: Number of iterations to run\n        bounds: Bounds for the search space (min, max)\n\n    Returns:\n        Tuple of (best_x, best_y, best_value)\n    \"\"\"\n    # Initialize with random point (simplified)\n    best_x, best_y = np.random.uniform(*bounds, 2)\n    best_value = evaluate_function(best_x, best_y)\n\n    for _ in range(iterations):\n        # Balance exploration (global search) and exploitation (local refinement)\n        if np.random.random() < 0.7:  # 70% local exploitation\n            # Adaptive step size that decreases over time\n            step = 0.1 * (1 - _/iterations) * (bounds[1] - bounds[0])\n            x, y = np.clip([best_x, best_y] + np.random.normal(0, step, 2), bounds[0], bounds[1])\n        else:  # 30% global exploration\n            x, y = np.random.uniform(*bounds, 2)\n            \n        value = evaluate_function(x, y)\n\n        if value < best_value:\n            best_value = value\n            best_x, best_y = x, y\n\n    return best_x, best_y, best_value\n\n\n# EVOLVE-BLOCK-END\n\n\n# This part remains fixed (not evolved)\ndef evaluate_function(x, y):\n    \"\"\"The complex function we're trying to minimize\"\"\"\n    return np.sin(x) * np.cos(y) + np.sin(x * y) + (x**2 + y**2) / 20\n\n\ndef run_search():\n    x, y, value = search_algorithm()\n    return x, y, value\n\n\nif __name__ == \"__main__\":\n    x, y, value = run_search()\n    print(f\"Found minimum at ({x}, {y}) with value {value}\")\n\n```\n\n# Task\nSuggest improvements to the program that will lead to better performance on the specified metrics.\n\nYou MUST use the exact SEARCH/REPLACE diff format shown below to indicate changes:\n\n<<<<<<< SEARCH\n# Original code to find and replace (must match exactly)\n=======\n# New replacement code\n>>>>>>> REPLACE\n\nExample of valid diff format:\n<<<<<<< SEARCH\nfor i in range(m):\n    for j in range(p):\n        for k in range(n):\n            C[i, j] += A[i, k] * B[k, j]\n=======\n# Reorder loops for better memory access pattern\nfor i in range(m):\n    for k in range(n):\n        for j in range(p):\n            C[i, j] += A[i, k] * B[k, j]\n>>>>>>> REPLACE\n\nYou can suggest multiple changes. Each SEARCH section must exactly match code in the current program.\nBe thoughtful about your changes and explain your reasoning thoroughly.\n\nIMPORTANT: Do not rewrite the entire program - focus on targeted improvements.\n", "responses": ["# Proposed Improvements\n\nTo improve code readability and maintainability while preserving excellent performance metrics, I'll simplify type annotations and add clarity to variable names and comments.\n\n## Change 1: Simplify Type Annotations\n```diff\n<<<<<<< SEARCH\nimport numpy as np\nfrom typing import Tuple\n\ndef search_algorithm(iterations: int = 1000, bounds: Tuple[float, float] = (-5, 5)) -> Tuple[float, float, float]:\n=======\nimport numpy as np\n\ndef search_algorithm(iterations=1000, bounds=(-5, 5)):\n>>>>>>> REPLACE\n```\n\nThis removes unnecessary type annotations that add complexity without clear benefit for this implementation, while maintaining the same functionality.\n\n## Change 2: Cache Bounds Values for Readability\n```diff\n<<<<<<< SEARCH\n    # Initialize with random point (simplified)\n    best_x, best_y = np.random.uniform(*bounds, 2)\n    best_value = evaluate_function(best_x, best_y)\n=======\n    # Cache bounds for readability and performance\n    lower, upper = bounds\n    range_size = upper - lower\n    \n    # Initialize with random point (simplified)\n    best_x, best_y = np.random.uniform(lower, upper, 2)\n    best_value = evaluate_function(best_x, best_y)\n>>>>>>> REPLACE\n```\n\nThis creates more readable variable names for the bounds and calculates the range size once, making subsequent code clearer and avoiding repeated calculations.\n\n## Change 3: Improve Loop Variable Name and Comments\n```diff\n<<<<<<< SEARCH\n    for _ in range(iterations):\n        # Balance exploration (global search) and exploitation (local refinement)\n        if np.random.random() < 0.7:  # 70% local exploitation\n            # Adaptive step size that decreases over time\n            step = 0.1 * (1 - _/iterations) * (bounds[1] - bounds[0])\n            x, y = np.clip([best_x, best_y] + np.random.normal(0, step, 2), bounds[0], bounds[1])\n        else:  # 30% global exploration\n            x, y = np.random.uniform(*bounds, 2)\n=======\n    for iteration in range(iterations):\n        # Balance exploration (global search) and exploitation (local refinement)\n        if np.random.random() < 0.7:  # 70% local exploitation\n            # Adaptive step size that decreases over time\n            step = 0.1 * (1 - iteration/iterations) * range_size\n            x, y = np.clip([best_x, best_y] + np.random.normal(0, step, 2), lower, upper)\n        else:  # 30% global exploration\n            x, y = np.random.uniform(lower, upper, 2)\n>>>>>>> REPLACE\n```\n\nThis replaces the vague `_` loop variable with a more descriptive `iteration` name and uses the pre-calculated bounds variables for cleaner, more readable code throughout the loop.\n\nThese changes maintain the algorithm's performance while making the code more approachable, easier to modify, and better documented through clearer variable names and structure."]}}}